lzma_c/__init__.py
lzma_c/_lzmamodule.c
lzma_c/_lzma.abi3.so
lzma_c-1.0.6.dist-info/METADATA
lzma_c-1.0.6.dist-info/RECORD
lzma_c-1.0.6.dist-info/top_level.txt
lzma_c-1.0.6.dist-info/WHEEL
