Metadata-Version: 2.1
Name: lzma-c
Version: 1.0.6
Summary: A fast LZMA compression library based on 7-Zip's C code
Author-email: alex <469370972@qq.com>
Classifier: Programming Language :: Python :: 3
Classifier: Operating System :: OS Independent
Requires-Python: >=3.7
